{
    "$schema": "https://json-schema.org/draft/2020-12/schema",
    "properties": {
        "argocd": {
            "properties": {
                "enabled": {
                    "type": "boolean"
                },
                "namespace": {
                    "type": "string"
                }
            },
            "type": "object"
        },
        "orchestrator": {
            "properties": {
                "namespace": {
                    "type": "string"
                },
                "sonataflowPlatform": {
                    "properties": {
                        "resources": {
                            "properties": {
                                "limits": {
                                    "properties": {
                                        "cpu": {
                                            "type": "string"
                                        },
                                        "memory": {
                                            "type": "string"
                                        }
                                    },
                                    "type": "object"
                                },
                                "requests": {
                                    "properties": {
                                        "cpu": {
                                            "type": "string"
                                        },
                                        "memory": {
                                            "type": "string"
                                        }
                                    },
                                    "type": "object"
                                }
                            },
                            "type": "object"
                        }
                    },
                    "type": "object"
                }
            },
            "type": "object"
        },
        "postgres": {
            "properties": {
                "authSecret": {
                    "properties": {
                        "name": {
                            "type": "string"
                        },
                        "passwordKey": {
                            "type": "string"
                        },
                        "userKey": {
                            "type": "string"
                        }
                    },
                    "type": "object"
                },
                "database": {
                    "type": "string"
                },
                "serviceName": {
                    "type": "string"
                },
                "serviceNamespace": {
                    "type": "string"
                }
            },
            "type": "object"
        },
        "rhdhOperator": {
            "properties": {
                "enableGuestProvider": {
                    "type": "boolean"
                },
                "enabled": {
                    "type": "boolean"
                },
                "isReleaseCandidate": {
                    "type": "boolean"
                },
                "secretRef": {
                    "properties": {
                        "argocd": {
                            "properties": {
                                "password": {
                                    "type": "string"
                                },
                                "url": {
                                    "type": "string"
                                },
                                "username": {
                                    "type": "string"
                                }
                            },
                            "type": "object"
                        },
                        "backstage": {
                            "properties": {
                                "backendSecret": {
                                    "type": "string"
                                }
                            },
                            "type": "object"
                        },
                        "github": {
                            "properties": {
                                "clientId": {
                                    "type": "string"
                                },
                                "clientSecret": {
                                    "type": "string"
                                },
                                "token": {
                                    "type": "string"
                                }
                            },
                            "type": "object"
                        },
                        "k8s": {
                            "properties": {
                                "clusterToken": {
                                    "type": "string"
                                },
                                "clusterUrl": {
                                    "type": "string"
                                }
                            },
                            "type": "object"
                        },
                        "name": {
                            "type": "string"
                        }
                    },
                    "type": "object"
                },
                "subscription": {
                    "properties": {
                        "channel": {
                            "type": "string"
                        },
                        "installPlanApproval": {
                            "type": "string"
                        },
                        "name": {
                            "type": "string"
                        },
                        "namespace": {
                            "type": "string"
                        },
                        "source": {
                            "type": "string"
                        },
                        "startingCSV": {
                            "type": "string"
                        }
                    },
                    "type": "object"
                }
            },
            "type": "object"
        },
        "rhdhPlugins": {
            "properties": {
                "notifications": {
                    "properties": {
                        "integrity": {
                            "type": "string"
                        },
                        "package": {
                            "type": "string"
                        }
                    },
                    "type": "object"
                },
                "notifications_backend": {
                    "properties": {
                        "integrity": {
                            "type": "string"
                        },
                        "package": {
                            "type": "string"
                        }
                    },
                    "type": "object"
                },
                "notifications_email": {
                    "properties": {
                        "integrity": {
                            "type": "string"
                        },
                        "package": {
                            "type": "string"
                        }
                    },
                    "type": "object"
                },
                "npmRegistry": {
                    "type": "string"
                },
                "orchestrator": {
                    "properties": {
                        "integrity": {
                            "type": "string"
                        },
                        "package": {
                            "type": "string"
                        }
                    },
                    "type": "object"
                },
                "orchestrator_backend": {
                    "properties": {
                        "integrity": {
                            "type": "string"
                        },
                        "package": {
                            "type": "string"
                        }
                    },
                    "type": "object"
                },
                "scope": {
                    "type": "string"
                },
                "signals": {
                    "properties": {
                        "integrity": {
                            "type": "string"
                        },
                        "package": {
                            "type": "string"
                        }
                    },
                    "type": "object"
                },
                "signals_backend": {
                    "properties": {
                        "integrity": {
                            "type": "string"
                        },
                        "package": {
                            "type": "string"
                        }
                    },
                    "type": "object"
                }
            },
            "type": "object"
        },
        "rhsso": {
            "properties": {
                "baseURL": {
                    "type": "string"
                },
                "client": {
                    "properties": {
                        "password": {
                            "type": "string"
                        },
                        "username": {
                            "type": "string"
                        }
                    },
                    "type": "object"
                },
                "deploy": {
                    "type": "boolean"
                },
                "enabled": {
                    "type": "boolean"
                },
                "instances": {
                    "type": "integer"
                },
                "log_level": {
                    "type": "string"
                },
                "metadataURL": {
                    "type": "string"
                },
                "namespace": {
                    "type": "string"
                },
                "realm": {
                    "properties": {
                        "name": {
                            "type": "string"
                        }
                    },
                    "type": "object"
                },
                "startingCSV": {
                    "type": "string"
                },
                "users": {
                    "items": {
                        "properties": {
                            "email": {
                                "type": "string"
                            },
                            "name": {
                                "type": "string"
                            },
                            "password": {
                                "type": "string"
                            }
                        },
                        "type": "object"
                    },
                    "type": "array"
                }
            },
            "type": "object"
        },
        "serverlessOperator": {
            "properties": {
                "enabled": {
                    "type": "boolean"
                },
                "subscription": {
                    "properties": {
                        "channel": {
                            "type": "string"
                        },
                        "installPlanApproval": {
                            "type": "string"
                        },
                        "name": {
                            "type": "string"
                        },
                        "namespace": {
                            "type": "string"
                        },
                        "sourceName": {
                            "type": "string"
                        }
                    },
                    "type": "object"
                }
            },
            "type": "object"
        },
        "sonataFlowOperator": {
            "properties": {
                "enabled": {
                    "type": "boolean"
                },
                "isReleaseCandidate": {
                    "type": "boolean"
                },
                "subscription": {
                    "properties": {
                        "channel": {
                            "type": "string"
                        },
                        "installPlanApproval": {
                            "type": "string"
                        },
                        "name": {
                            "type": "string"
                        },
                        "namespace": {
                            "type": "string"
                        },
                        "sourceName": {
                            "type": "string"
                        },
                        "startingCSV": {
                            "type": "string"
                        }
                    },
                    "type": "object"
                }
            },
            "type": "object"
        },
        "tekton": {
            "properties": {
                "enabled": {
                    "type": "boolean"
                }
            },
            "type": "object"
        }
    },
    "type": "object"
}
